{
  "project_info": {
    "project_id": "gerdoo-a6f3f",
    "project_number": "772045087067",
    "name": "Gerdoo"
  },
  "client": [
    {
      "client_info": {
        "mobilesdk_app_id": "1:772045087067:android:8446a20938b2ed92",
        "client_id": "android:com.anashidgames.gerdoo",
        "client_type": 1,
        "android_client_info": {
          "package_name": "com.anashidgames.gerdoo",
          "certificate_hash": []
        }
      },
      "oauth_client": [
        {
          "client_id": "772045087067-riav8qiihnm7ospfg5dtaqfh6vtfi6c8.apps.googleusercontent.com",
          "client_type": 1,
          "android_info": {
            "package_name": "com.anashidgames.gerdoo",
            "certificate_hash": "47584EA095A478AC8E4658565CA377806169250D"
          }
        },
        {
          "client_id": "772045087067-a2u91ltl9hdpid8fjrneorhv7aia8v8a.apps.googleusercontent.com",
          "client_type": 3
        }
      ],
      "api_key": [],
      "services": {
        "analytics_service": {
          "status": 1
        },
        "cloud_messaging_service": {
          "status": 1,
          "apns_config": []
        },
        "appinvite_service": {
          "status": 1,
          "other_platform_oauth_client": []
        },
        "google_signin_service": {
          "status": 2
        },
        "ads_service": {
          "status": 1
        }
      }
    }
  ],
  "client_info": [],
  "ARTIFACT_VERSION": "1"
}